pryngles/__init__.py
pryngles/body.py
pryngles/consts.py
pryngles/cpixx.cpython-312-darwin.so
pryngles/extensions.py
pryngles/header.py
pryngles/legacy.py
pryngles/misc.py
pryngles/orbit.py
pryngles/plot.py
pryngles/sampler.py
pryngles/scatterer.py
pryngles/science.py
pryngles/spangler.py
pryngles/system.py
pryngles/version.py
pryngles/cpixx/cpixx.c
pryngles/data/diffuse_reflection_function.data
pryngles/data/fou_gasplanet.dat
pryngles/data/fou_gasplanet_optical_50.dat
pryngles/data/fou_lambert.dat
pryngles/data/fou_ring_0_4_0_8.dat
pryngles/data/fou_ring_0_4_0_8_20gaus.dat
pryngles/data/ring-interpolation.mat
pryngles/data/sampler_presets/sample_circle_N_100.pkl
pryngles/data/sampler_presets/sample_circle_N_1000.pkl
pryngles/data/sampler_presets/sample_circle_N_1100.pkl
pryngles/data/sampler_presets/sample_circle_N_1200.pkl
pryngles/data/sampler_presets/sample_circle_N_1300.pkl
pryngles/data/sampler_presets/sample_circle_N_1400.pkl
pryngles/data/sampler_presets/sample_circle_N_1500.pkl
pryngles/data/sampler_presets/sample_circle_N_1600.pkl
pryngles/data/sampler_presets/sample_circle_N_1700.pkl
pryngles/data/sampler_presets/sample_circle_N_1800.pkl
pryngles/data/sampler_presets/sample_circle_N_1900.pkl
pryngles/data/sampler_presets/sample_circle_N_200.pkl
pryngles/data/sampler_presets/sample_circle_N_2000.pkl
pryngles/data/sampler_presets/sample_circle_N_2100.pkl
pryngles/data/sampler_presets/sample_circle_N_2200.pkl
pryngles/data/sampler_presets/sample_circle_N_2300.pkl
pryngles/data/sampler_presets/sample_circle_N_2400.pkl
pryngles/data/sampler_presets/sample_circle_N_2500.pkl
pryngles/data/sampler_presets/sample_circle_N_2600.pkl
pryngles/data/sampler_presets/sample_circle_N_2700.pkl
pryngles/data/sampler_presets/sample_circle_N_2800.pkl
pryngles/data/sampler_presets/sample_circle_N_2900.pkl
pryngles/data/sampler_presets/sample_circle_N_300.pkl
pryngles/data/sampler_presets/sample_circle_N_3000.pkl
pryngles/data/sampler_presets/sample_circle_N_3100.pkl
pryngles-0.9.12.dist-info/licenses/LICENSE
pryngles-0.9.12.dist-info/METADATA
pryngles-0.9.12.dist-info/WHEEL
pryngles-0.9.12.dist-info/entry_points.txt
pryngles-0.9.12.dist-info/top_level.txt
pryngles-0.9.12.dist-info/RECORD
