Metadata-Version: 2.4
Name: pryngles
Version: 0.9.12
Summary: PlanetaRY spanGLES: general photometry of planets, rings and shadows
Home-page: https://pypi.org/project/pryngles
Author: Jorge I. Zuluaga, Allard Veenstra, Sebastian Numpaque, Mario Sucerquia and Jaime A. Alvarado-Montes
Author-email: jorge.zuluaga@udea.edu.co
License: MIT
Keywords: astronomy exoplanets planetary-rings
Classifier: Programming Language :: Python :: 3
Classifier: License :: OSI Approved :: MIT License
Classifier: Operating System :: OS Independent
License-File: LICENSE
Requires-Dist: rebound
Requires-Dist: scipy
Requires-Dist: ipython
Requires-Dist: matplotlib
Requires-Dist: tqdm
Requires-Dist: dill
Requires-Dist: spiceypy
Requires-Dist: cmasher
Requires-Dist: pandas
Requires-Dist: celluloid
Requires-Dist: sigfig
Requires-Dist: anytree
Requires-Dist: ipywidgets
Requires-Dist: gdown
Dynamic: author
Dynamic: author-email
Dynamic: classifier
Dynamic: description
Dynamic: description-content-type
Dynamic: home-page
Dynamic: keywords
Dynamic: license
Dynamic: license-file
Dynamic: requires-dist
Dynamic: summary
